tlshttp/__init__.py
tlshttp/_client.py
tlshttp/_cookies.py
tlshttp/_exceptions.py
tlshttp/_headers.py
tlshttp/_request.py
tlshttp/_response.py
tlshttp/_types.py
tlshttp/_internal/__init__.py
tlshttp/_internal/_downloader.py
tlshttp/_internal/_library.py
tlshttp/_internal/_platform.py
tlshttp/_internal/_protocol.py
tlshttp/_internal/_session.py
tlshttp/profiles/__init__.py
tlshttp/profiles/_browsers.py
tlshttp-0.2.0.dist-info/METADATA
tlshttp-0.2.0.dist-info/WHEEL
tlshttp-0.2.0.dist-info/licenses/LICENSE
tlshttp-0.2.0.dist-info/RECORD
