Metadata-Version: 2.4
Name: tlshttp
Version: 0.2.0
Summary: Modern Python wrapper for tls-client with httpx-like API and browser fingerprinting
Project-URL: Homepage, https://github.com/yourusername/tlshttp
Project-URL: Documentation, https://github.com/yourusername/tlshttp#readme
Project-URL: Repository, https://github.com/yourusername/tlshttp
Author-email: Your Name <you@example.com>
License-Expression: MIT
License-File: LICENSE
Keywords: fingerprint,http,httpx,requests,scraping,tls
Classifier: Development Status :: 4 - Beta
Classifier: Intended Audience :: Developers
Classifier: License :: OSI Approved :: MIT License
Classifier: Programming Language :: Python :: 3
Classifier: Programming Language :: Python :: 3.10
Classifier: Programming Language :: Python :: 3.11
Classifier: Programming Language :: Python :: 3.12
Classifier: Programming Language :: Python :: 3.13
Classifier: Topic :: Internet :: WWW/HTTP
Classifier: Typing :: Typed
Requires-Python: >=3.10
Requires-Dist: anyio>=4.0
Requires-Dist: platformdirs>=3.0
Provides-Extra: dev
Requires-Dist: pytest-anyio>=0.0.0; extra == 'dev'
Requires-Dist: pytest-mock>=3.0; extra == 'dev'
Requires-Dist: pytest>=8.0; extra == 'dev'
